setup.py
obhm/__init__.py
obhm/load.py
obhm/server.py
obhm.egg-info/PKG-INFO
obhm.egg-info/SOURCES.txt
obhm.egg-info/dependency_links.txt
obhm.egg-info/requires.txt
obhm.egg-info/top_level.txt
obhm.egg-info/zip-safe
scripts/obhm