Metadata-Version: 1.0
Name: obhm
Version: 0.0.1
Summary: One Banana Host Monitoring for people with other things to think about
Home-page: https://github.com/ob/obhm
Author: Adam DePrince
Author-email: adeprince@nypublicradio.org
License: UNKNOWN
Platform: UNKNOWN
